[{"__type__":"cc.SpriteFrame","content":{"name":"duihao1","texture":"0ammMdmLpIqo5N007YR17q","rect":[37,38,126,124],"offset":[0,0],"originalSize":[200,200]}},{"__type__":"cc.SpriteFrame","content":{"name":"default_btn_disabled","texture":"71VhFCTINJM6/Ky3oX9nBT","rect":[0,0,40,40],"offset":[0,0],"originalSize":[40,40],"capInsets":[15,7,15,9]}},{"__type__":"cc.SpriteFrame","content":{"name":"yuanjiao","texture":"f4LMvwk4BClZS8D5YqQYZp","rect":[0,0,300,300],"offset":[0,0],"originalSize":[300,300],"capInsets":[75,42,81,80]}},{"__type__":"cc.SpriteFrame","content":{"name":"testTEST","texture":"cd9DneuBJIbr2L8HVHBFgI","rect":[0,0,255,256],"offset":[-0.5,0],"originalSize":[256,256]}},{"__type__":"cc.SpriteFrame","content":{"name":"Gift_box","texture":"13W3sF5NVNB7slPmT/EgkT","rect":[0,0,214,272],"offset":[0,0],"originalSize":[214,272]}},[{"__type__":"cc.Prefab","_name":"getGifyBoxTip","data":{"__id__":1},"asyncLoadAssets":null},{"__type__":"cc.Node","_name":"getGifyBoxTip","_children":[{"__id__":2},{"__id__":3},{"__id__":4},{"__id__":5},{"__id__":6},{"__id__":8},{"__id__":9},{"__id__":10},{"__id__":11}],"_components":[{"__type__":"62c8fxs/PFLgpI6/Zdex4bf","node":{"__id__":1},"guang":{"__id__":10}}],"_prefab":{"__type__":"cc.PrefabInfo","root":{"__id__":1},"asset":{"__uuid__":"c5EQVstIRNs67OB5b5SGKI"},"fileId":"26+H+Ku91L0YAxEqnkLK03"}},{"__type__":"cc.Node","_name":"bg","_parent":{"__id__":1},"_components":[{"__type__":"cc.Sprite","node":{"__id__":2},"_spriteFrame":{"__uuid__":"fbugIPSiVAf5flu1slG8L2"},"_sizeMode":0}],"_prefab":{"__type__":"cc.PrefabInfo","root":{"__id__":1},"asset":{"__uuid__":"c5EQVstIRNs67OB5b5SGKI"},"fileId":"0a0EKall9Kl68B8rv2pFbu"},"_opacity":150,"_color":{"__type__":"cc.Color","r":14,"g":13,"b":13},"_contentSize":{"__type__":"cc.Size","width":720,"height":1280}},{"__type__":"cc.Node","_name":"bg1","_parent":{"__id__":1},"_components":[{"__type__":"cc.Sprite","node":{"__id__":3},"_spriteFrame":{"__uuid__":"35J5LVb8dCgpsTrz5LTOAl"},"_type":1,"_sizeMode":0}],"_prefab":{"__type__":"cc.PrefabInfo","root":{"__id__":1},"asset":{"__uuid__":"c5EQVstIRNs67OB5b5SGKI"},"fileId":"300QhwBV5NiZQFoVso/asc"},"_color":{"__type__":"cc.Color","r":49,"g":192,"b":36},"_contentSize":{"__type__":"cc.Size","width":600,"height":400},"_position":{"__type__":"cc.Vec2","y":89}},{"__type__":"cc.Node","_name":"Background_2","_parent":{"__id__":1},"_components":[{"__type__":"cc.Sprite","node":{"__id__":4},"_spriteFrame":{"__uuid__":"35J5LVb8dCgpsTrz5LTOAl"},"_type":1,"_sizeMode":0}],"_prefab":{"__type__":"cc.PrefabInfo","root":{"__id__":1},"asset":{"__uuid__":"c5EQVstIRNs67OB5b5SGKI"},"fileId":"88rwui5RVODJNjSb/ORPhH"},"_contentSize":{"__type__":"cc.Size","width":585,"height":300},"_position":{"__type__":"cc.Vec2","y":46}},{"__type__":"cc.Node","_name":"title","_parent":{"__id__":1},"_components":[{"__type__":"cc.Label","node":{"__id__":5},"_useOriginalSize":false,"_N$string":"你成功获得了一个神秘礼盒","_N$horizontalAlign":1,"_N$verticalAlign":1}],"_prefab":{"__type__":"cc.PrefabInfo","root":{"__id__":1},"asset":{"__uuid__":"c5EQVstIRNs67OB5b5SGKI"},"fileId":"87/f7WiN9KiZLi4AFoKRXJ"},"_contentSize":{"__type__":"cc.Size","width":480,"height":40},"_position":{"__type__":"cc.Vec2","y":86}},{"__type__":"cc.Node","_name":"ensure","_parent":{"__id__":1},"_children":[{"__id__":7}],"_components":[{"__type__":"cc.Sprite","node":{"__id__":6},"_spriteFrame":{"__uuid__":"35J5LVb8dCgpsTrz5LTOAl"},"_type":1,"_sizeMode":0},{"__type__":"cc.Button","node":{"__id__":6},"transition":3,"pressedColor":{"__type__":"cc.Color","r":255,"g":255,"b":255},"_N$normalColor":{"__type__":"cc.Color","r":255,"g":255,"b":255},"_N$disabledColor":{"__type__":"cc.Color","r":255,"g":255,"b":255},"_N$normalSprite":{"__uuid__":"35J5LVb8dCgpsTrz5LTOAl"},"_N$pressedSprite":{"__uuid__":"e97GVMl6JHh5Ml5qEDdSGa"},"pressedSprite":{"__uuid__":"e97GVMl6JHh5Ml5qEDdSGa"},"_N$hoverSprite":{"__uuid__":"e97GVMl6JHh5Ml5qEDdSGa"},"hoverSprite":{"__uuid__":"e97GVMl6JHh5Ml5qEDdSGa"},"_N$disabledSprite":{"__uuid__":"29FYIk+N1GYaeWH/q1NxQO"},"_N$target":{"__id__":6}}],"_prefab":{"__type__":"cc.PrefabInfo","root":{"__id__":1},"asset":{"__uuid__":"c5EQVstIRNs67OB5b5SGKI"},"fileId":"52GpnMOwJNB4p0xUJzqooI"},"_color":{"__type__":"cc.Color","r":20,"g":182,"b":39},"_contentSize":{"__type__":"cc.Size","width":150,"height":120},"_position":{"__type__":"cc.Vec2","x":-2,"y":-14}},{"__type__":"cc.Node","_name":"duihao","_parent":{"__id__":6},"_components":[{"__type__":"cc.Sprite","node":{"__id__":7},"_spriteFrame":{"__uuid__":"22UV4vNGVNrZQtd4KF4F3W"},"_sizeMode":0}],"_prefab":{"__type__":"cc.PrefabInfo","root":{"__id__":1},"asset":{"__uuid__":"c5EQVstIRNs67OB5b5SGKI"},"fileId":"a1vTf4MtNA7Zy/s2+BVZKD"},"_contentSize":{"__type__":"cc.Size","width":80,"height":80}},{"__type__":"cc.Node","_name":"Title","_parent":{"__id__":1},"_components":[{"__type__":"cc.Label","node":{"__id__":8},"_useOriginalSize":false,"_N$string":"成功","_N$horizontalAlign":1,"_N$verticalAlign":1}],"_prefab":{"__type__":"cc.PrefabInfo","root":{"__id__":1},"asset":{"__uuid__":"c5EQVstIRNs67OB5b5SGKI"},"fileId":"52radDfpBI5748qJVdf+k4"},"_contentSize":{"__type__":"cc.Size","width":80,"height":40},"_position":{"__type__":"cc.Vec2","y":235}},{"__type__":"cc.Node","_name":"content","_parent":{"__id__":1},"_components":[{"__type__":"cc.Label","node":{"__id__":9},"_useOriginalSize":false,"_actualFontSize":30,"_fontSize":30,"_N$file":{"__uuid__":"67yJV1XrFE0KON+ZRwUbCu"},"_isSystemFontUsed":false,"_N$string":"你刚刚获得了一个免费礼盒，\n等会回来可继续领取另一个哦！","_N$horizontalAlign":1,"_N$verticalAlign":1}],"_prefab":{"__type__":"cc.PrefabInfo","root":{"__id__":1},"asset":{"__uuid__":"c5EQVstIRNs67OB5b5SGKI"},"fileId":"ccYUpzQHFIQ6o6NBXnohvV"},"_color":{"__type__":"cc.Color","r":231,"g":37,"b":10},"_contentSize":{"__type__":"cc.Size","width":420,"height":80},"_position":{"__type__":"cc.Vec2","y":118},"_skewX":5},{"__type__":"cc.Node","_name":"guang","_parent":{"__id__":1},"_components":[{"__type__":"cc.Sprite","node":{"__id__":10},"_spriteFrame":{"__uuid__":"68iyKxhJRL6YZ6atidvd/j"},"_sizeMode":0}],"_prefab":{"__type__":"cc.PrefabInfo","root":{"__id__":1},"asset":{"__uuid__":"c5EQVstIRNs67OB5b5SGKI"},"fileId":"d7nFqSOpNHxKzU0XMAdig6"},"_contentSize":{"__type__":"cc.Size","width":150,"height":150},"_position":{"__type__":"cc.Vec2","x":206,"y":235}},{"__type__":"cc.Node","_name":"giftBox","_parent":{"__id__":1},"_components":[{"__type__":"cc.Sprite","node":{"__id__":11},"_spriteFrame":{"__uuid__":"6fLQBF6wRCkbEZ1H9rboAz"},"_sizeMode":0}],"_prefab":{"__type__":"cc.PrefabInfo","root":{"__id__":1},"asset":{"__uuid__":"c5EQVstIRNs67OB5b5SGKI"},"fileId":"f9rb7rciFKqoN6Gv5eEwxz"},"_contentSize":{"__type__":"cc.Size","width":70,"height":70},"_position":{"__type__":"cc.Vec2","x":208,"y":243}}],{"__type__":"cc.SpriteFrame","content":{"name":"default_btn_pressed","texture":"b4P/PCArtIdIH38t6mlw8Y","rect":[0,0,40,40],"offset":[0,0],"originalSize":[40,40],"capInsets":[11,11,11,7]}},{"__type__":"cc.SpriteFrame","content":{"name":"huodong_1","texture":"7eX+D7popIH4owRcXyPGCE","rect":[0,0,93,94],"offset":[0,0],"originalSize":[93,94]}}]